<uresolver_content xmlns="http://com/exlibris/urm/uresolver/xmlbeans/u" xmlns:xsi="http://www.w3.org/2001/XMLSchema-instance">
  <context_object>
    <keys>
      <key id="ctx_enc">info:ofi/enc:UTF-8</key>
      <key id="rft_val_fmt">info:ofi/fmt:kev:mtx:book</key>
      <key id="rft.stitle">Oxford research encyclopedia of politics /</key>
      <key id="rft.place">New York, NY :</key>
      <key id="available_services">viewit</key>
      <key id="available_services">getit</key>
      <key id="rft.btitle">Oxford research encyclopedia of politics /</key>
      <key id="rft.isbn_13">978-0-19-022863-7</key>
      <key id="rft.genre">bookitem</key>
      <key id="rft.aufirst">Jacqueline H R</key>
      <key id="rft.isbn_10">0-19-022863-6</key>
      <key id="Incoming_URL">http%3A%2F%2Fna04.alma.exlibrisgroup.com%2Fview%2Furesolver%2F01UMICH_INST%2Fopenurl%3Fdebug%3Dtrue%26ctx_enc%3Dinfo%3Aofi%2Fenc%3AUTF-8%26ctx_id%3D10_1%26ctx_tim%3D2024-10-22%252014%3A04%3A37%26ctx_ver%3DZ39.88-2004%26rfr_id%3Dinfo%3Asid%2Fprimo.exlibrisgroup.com-oup%26rft.atitle%3DThe%2520Strategic%2520Use%2520of%2520State%2520Repression%2520and%2520Political%2520Violence%26rft.au%3DJacqueline%2520H.%2520R.%2520deMeritt%26rft.btitle%3DOxford%2520Research%2520Encyclopedia%2520of%2520Politics%26rft.date%3D2016-10-26%26rft.genre%3Dchapter%26rft.isbn%3D0190228636%26rft.pub%3DOxford%2520University%2520Press%26rft.rft_oup_id%3D10_1093_acrefore_9780190228637_013_32%26rft.utm_source%3Dlibrary-search%26rft_dat%3D%253Coup%253E10_1093_acrefore_9780190228637_013_32%253C%2Foup%253E%26rft_id%3Dinfo%3Adoi%2F10.1093%2Facrefore%2F9780190228637.013.32%26rft_val_fmt%3Dinfo%3Aofi%2Ffmt%3Akev%3Amtx%3Abook%26svc_dat%3DCTO%26url_ctx_fmt%3Dinfo%3Aofi%2Ffmt%3Akev%3Amtx%3Actx%26url_ver%3DZ39.88-2004</key>
      <key id="institution">6381</key>
      <key id="rft.normalized_isbn">9780190228637</key>
      <key id="rft.eisbn_10">0-19-022863-6</key>
      <key id="http_request_type">GET</key>
      <key id="rft.eisbn_13">978-0-19-022863-7</key>
      <key id="rft.normalized_eisbn">9780190228637</key>
      <key id="rft.doi">10.1093/acrefore/9780190228637.013.32</key>
      <key id="prefer_ordered_resources">false</key>
      <key id="rft.year">2016</key>
      <key id="req.id" xsi:nil="true"/>
      <key id="user_ip" xsi:nil="true"/>
      <key id="rft_id">info:doi/10.1093/acrefore/9780190228637.013.32</key>
      <key id="inventory_id">511123329560006381</key>
      <key id="rft.inventory_id">511123329560006381</key>
      <key id="sfx.primo_docID">1093</key>
      <key id="rft.aulast">deMeritt</key>
      <key id="publication_place">New York, NY :</key>
      <key id="rft.object_type">BOOK</key>
      <key id="url_ver">Z39.88-2004</key>
      <key id="rft.date">2016-10-26</key>
      <key id="rft.utm_source">library-search</key>
      <key id="ctx_id">10_1</key>
      <key id="ctx_id">80449425880006381</key>
      <key id="full_text_indicator">true</key>
      <key id="rft_dat">&lt;oup>10_1093_acrefore_9780190228637_013_32&lt;/oup></key>
      <key id="rft.title">Oxford research encyclopedia of politics /</key>
      <key id="rft.pub">Oxford University Press,</key>
      <key id="ctx_tim">2024-10-22 14:04:37</key>
      <key id="ctx_ver">Z39.88-2004</key>
      <key id="licenseEnable">false</key>
      <key id="rft.isbn">0190228636</key>
      <key id="rft.isbn">9780190228637</key>
      <key id="sfx.sid">primo.exlibrisgroup.com-oup</key>
      <key id="sfx.primo_docTAG">oup</key>
      <key id="url_ctx_fmt">info:ofi/fmt:kev:mtx:ctx</key>
      <key id="sfx.doi_url">https://doi.org</key>
      <key id="rft.mms_id">99187397324106381</key>
      <key id="rft.day">26</key>
      <key id="rft.month">10</key>
      <key id="rfr_id">info:sid/primo.exlibrisgroup.com-oup</key>
      <key id="rft.eisbn">9780190228637</key>
      <key id="rft.rft_oup_id">10_1093_acrefore_9780190228637_013_32</key>
      <key id="rft.publisher">Oxford University Press,</key>
      <key id="rft.au">Jacqueline H. R. deMeritt</key>
      <key id="rft.au">deMeritt, Jacqueline H R</key>
      <key id="rft.au">deMeritt, Jacqueline H R</key>
      <key id="rft.pubdate">[2014-]</key>
      <key id="rft.atitle">The Strategic Use of State Repression and Political Violence</key>
      <key id="customer">6380</key>
      <key id="rfr.rfr">primo.exlibrisgroup.com-oup</key>
    </keys>
  </context_object>
  <context_services>
    <context_service service_type="getFullTxt" context_service_id="80443569570006381">
      <keys>
        <key id="package_name">Oxford Research Encyclopedias</key>
        <key id="package_public_name">Oxford Research Encyclopedias</key>
        <key id="package_original_name">Oxford Research Encyclopedias</key>
        <key id="package_display_name">Oxford Research Encyclopedias</key>
        <key id="package_internal_name">OXFORD_RESEARCH_ENCYCLOPEDIAS</key>
        <key id="interface_name">Oxford Research Encyclopedias</key>
        <key id="db_id">BJ0, ACLSJ</key>
        <key id="package_pid">611072807510006381</key>
        <key id="service_type_description">Full text available via</key>
        <key id="character_set">iso-8859-1</key>
        <key id="Is_free">0</key>
        <key id="request_source">oup</key>
        <key id="portfolio_PID">531123329460006381</key>
        <key id="cz_link_id">534330000001732424</key>
        <key id="electronic_material_type">BOOK</key>
        <key id="Availability"/>
        <key id="static_url">false</key>
        <key id="parser_program">Bulk::BULKdoi</key>
        <key id="parse_parameters">bkey=https://oxfordre.com/politics</key>
        <key id="Authentication_note">Authorized U-M users (+ guests in U-M Libraries).&lt;br/></key>
        <key id="public_note"/>
        <key id="proxy_enabled">true</key>
        <key id="proxy_selected">DEFAULT</key>
        <key id="related_title">@TITLE (@RelationType)</key>
        <key id="is_related_service">false</key>
        <key id="is_closly_related">false</key>
        <key id="license_exist">false</key>
        <key id="crossref_enabled">yes</key>
        <key id="preferred_link">false</key>
      </keys>
      <resolution_url>https://umich.alma.exlibrisgroup.com/view/action/uresolver.do?operation=resolveService&amp;package_service_id=80443569570006381&amp;institutionId=6381&amp;customerId=6380</resolution_url>
    </context_service>
  </context_services>
  <performance_counters>
    <performance_counter name="TOTAL" duration="0.0"/>
    <performance_counter name="MMS_LOOKUP" duration="1.52"/>
    <performance_counter name="ENRICH" duration="0.0"/>
    <performance_counter name="PARSE" duration="0.0"/>
    <performance_counter name="GET_SERVICES" duration="0.006"/>
    <performance_counter name="FILTER" duration="0.005"/>
    <performance_counter name="SAVE" duration="0.005"/>
    <performance_counter name="GET_ZERO_TITLE_SERVICES" duration="0.0"/>
    <performance_counter name="FETCH_SERVICE_THRESHOLD_RULES" duration="0.0"/>
    <performance_counter name="CREATE_ZERO_TITLE_SERVICES" duration="0.0"/>
    <performance_counter name="SAVE_ZERO_TITLE_SERVICES" duration="0.0"/>
    <performance_counter name="GET_SINGLE_SERVICE" duration="0.0"/>
    <performance_counter name="EXECUTE_TARGET_PARSER" duration="0.0"/>
    <performance_counter name="GET_URESOLVER_CONTENT" duration="0.0"/>
    <performance_counter name="UPDATE_SELECTED" duration="0.0"/>
    <performance_counter name="AF_GROUPS_ENRICHMENT" duration="0.0"/>
  </performance_counters>
</uresolver_content>